mouse_analysis/__init__.py
mouse_analysis/distance.py
mouse_analysis-0.1.0.dist-info/METADATA
mouse_analysis-0.1.0.dist-info/WHEEL
mouse_analysis-0.1.0.dist-info/top_level.txt
mouse_analysis-0.1.0.dist-info/RECORD
