Metadata-Version: 2.1
Name: mouse-analysis
Version: 0.1.0
Summary: A package for analyzing mouse behavior.
Home-page: https://github.com/yourusername/mouse_analysis
Author: Fengxi Jin
Author-email: fengxi.jin@manchester.ac.uk
Classifier: Programming Language :: Python :: 3
Classifier: License :: OSI Approved :: MIT License
Classifier: Operating System :: OS Independent
Requires-Python: >=3.6
Requires-Dist: numpy >=1.15
